{
    "pension_type": "retirement_standard",
    "personal_data": {
        "full_name": "Аникита Антипович Зыков",
        "birth_date": "29.04.1971",
        "snils": "387-063-720 10",
        "gender": "male",
        "citizenship": "Российская Федерация",
        "name_change_info": {
            "old_full_name": "Сысоев Анисим Егорович",
            "date_changed": "07.09.2022"
        },
        "dependents": 0
    },
    "work_experience": {
        "total_years": 9,
        "records": [
            {
                "organization": "ИП «Абрамова»",
                "start_date": "26.07.1986",
                "end_date": "16.12.2002",
                "position": "Инженер-гидравлик",
                "special_conditions": false
            },
            {
                "organization": "Ланит",
                "start_date": "21.10.2005",
                "end_date": "18.06.2024",
                "position": "Сценарист",
                "special_conditions": true
            },
            {
                "organization": "ООО «Исакова»",
                "start_date": "31.08.1990",
                "end_date": "05.02.2002",
                "position": "Хирург",
                "special_conditions": true
            }
        ]
    },
    "pension_points": 9.15,
    "disability": null,
    "benefits": [
        "Ветеран труда",
        "Инвалид 2 группы"
    ],
    "documents": [
        "Справка о стаже",
        "Справка МСЭ",
        "СНИЛС",
        "Трудовая книжка",
        "Паспорт",
        "Военный билет"
    ],
    "has_incorrect_document": false
}