{
    "pension_type": "disability_social",
    "personal_data": {
        "full_name": "Евстафий Жанович Шашков",
        "birth_date": "07.12.1971",
        "snils": "171-230-914 49",
        "gender": "male",
        "citizenship": "Беларусь",
        "name_change_info": {
            "old_full_name": "Белова Алевтина Владиславовна",
            "date_changed": "06.10.2023"
        },
        "dependents": 0
    },
    "work_experience": {
        "total_years": 0,
        "records": []
    },
    "pension_points": 0,
    "disability": {
        "group": "2",
        "date": "2021-04-24",
        "cert_number": null
    },
    "benefits": [],
    "documents": [
        "Паспорт",
        "СНИЛС",
        "Справка МСЭ",
        "Трудовая книжка",
        "Справка о стаже",
        "Военный билет"
    ],
    "has_incorrect_document": false
}