{
    "pension_type": "retirement_standard",
    "personal_data": {
        "full_name": "Пантелеймон Абрамович Горшков",
        "birth_date": "11.12.1960",
        "snils": "608-293-497 69",
        "gender": "male",
        "citizenship": "Российская Федерация",
        "name_change_info": {
            "old_full_name": "Татьяна Петровна Тарасова",
            "date_changed": "07.05.2020"
        },
        "dependents": 3
    },
    "work_experience": {
        "total_years": 10,
        "records": [
            {
                "organization": "Модум-транс",
                "start_date": "12.07.1991",
                "end_date": "28.12.1992",
                "position": "Скульптор",
                "special_conditions": false
            },
            {
                "organization": "Л'Этуаль",
                "start_date": "13.07.1992",
                "end_date": "05.03.2020",
                "position": "Водитель",
                "special_conditions": true
            },
            {
                "organization": "НПО «Воробьева Бобылева»",
                "start_date": "01.09.2005",
                "end_date": "14.06.2017",
                "position": "Токсиколог",
                "special_conditions": false
            },
            {
                "organization": "АвтоВАЗ",
                "start_date": "29.12.2010",
                "end_date": "25.07.2018",
                "position": "Кинолог",
                "special_conditions": false
            },
            {
                "organization": "ООО «Щукин-Панова»",
                "start_date": "17.07.1985",
                "end_date": "12.12.2021",
                "position": "Декан",
                "special_conditions": true
            }
        ]
    },
    "pension_points": 23.39,
    "disability": null,
    "benefits": [
        "Многодетная мать",
        "Ветеран труда"
    ],
    "documents": [
        "Трудовая книжка",
        "Паспорт",
        "Военный билет",
        "Справка МСЭ",
        "Справка о стаже"
    ],
    "has_incorrect_document": false
}