{
    "pension_type": "retirement_standard",
    "personal_data": {
        "full_name": "Самуил Марсович Шашков",
        "birth_date": "23.02.1973",
        "snils": "342-369-838 19",
        "gender": "male",
        "citizenship": "Беларусь",
        "name_change_info": {
            "old_full_name": "Трофим Игнатович Осипов",
            "date_changed": "11.08.2021"
        },
        "dependents": 1
    },
    "work_experience": {
        "total_years": 5,
        "records": [
            {
                "organization": "ЗАО «Дроздов Тимофеев»",
                "start_date": "31.12.2017",
                "end_date": "24.12.2022",
                "position": "Донкерман",
                "special_conditions": false
            },
            {
                "organization": "ОАО «Егорова, Коновалов и Дмитриева»",
                "start_date": "30.03.2005",
                "end_date": "01.06.2013",
                "position": "Специалист по стрижке овец",
                "special_conditions": true
            },
            {
                "organization": "ООО «Мишин Муравьева»",
                "start_date": "21.04.1989",
                "end_date": "02.02.1995",
                "position": "Маркшейдер",
                "special_conditions": false
            },
            {
                "organization": "ЗАО «Жданова, Белоусова и Колобов»",
                "start_date": "25.09.1992",
                "end_date": "24.09.2006",
                "position": "Реаниматолог",
                "special_conditions": false
            },
            {
                "organization": "НПО «Рябова-Мишина»",
                "start_date": "20.09.1995",
                "end_date": "28.11.2009",
                "position": "Морской пехотинец",
                "special_conditions": false
            }
        ]
    },
    "pension_points": 5.78,
    "disability": null,
    "benefits": [],
    "documents": [
        "СНИЛС",
        "Паспорт",
        "Военный билет",
        "Справка о стаже",
        "Справка МСЭ"
    ],
    "has_incorrect_document": true
}